lstm_anomaly_tool/__init__.py
lstm_anomaly_tool/model.h5
lstm_anomaly_tool/predict.py
lstm_anomaly_tool/predict_anomalies.py
lstm_anomaly_tool/scaler.pkl
lstm_anomaly_tool/threshold.json
lstm_anomaly_tool-0.1.4.dist-info/METADATA
lstm_anomaly_tool-0.1.4.dist-info/WHEEL
lstm_anomaly_tool-0.1.4.dist-info/top_level.txt
lstm_anomaly_tool-0.1.4.dist-info/RECORD
